rustpy/option.py
rustpy/__init__.py
rustpy/_crustpy.cpython-310-darwin.so
rustpy/result.py
rustpy/primitive.py
rustpy/primitive.pyi
rustpy/py.typed
rustpy/result.pyi
rustpy/option.pyi
rustpy/_rustpy/option.py
rustpy/_rustpy/__init__.py
rustpy/_rustpy/result.py
rustpy/_rustpy/primitive.py
rustpy/_rustpy/_core/wrapper.py
rustpy/_rustpy/_core/float.py
rustpy/_rustpy/_core/number.py
rustpy/_rustpy/_core/__init__.py
rustpy/_rustpy/_core/integer.py
rustpy/_rustpy/_core/utils.py
rustpy/_rustpy/_core/ordered.py
rustpy/_rustpy/_core/bool_.py
rustpy-0.3.0.dist-info/RECORD
rustpy-0.3.0.dist-info/LICENSE
rustpy-0.3.0.dist-info/WHEEL
rustpy-0.3.0.dist-info/top_level.txt
rustpy-0.3.0.dist-info/METADATA
