Metadata-Version: 2.1
Name: rustpy
Version: 0.3.0
Home-page: https://github.com/lycantropos/rustpy/
Download-URL: https://github.com/lycantropos/rustpy/archive/master.zip
Author-email: Azat Ibrakov <azatibrakov@gmail.com>
License: MIT License
Classifier: License :: OSI Approved :: MIT License
Classifier: Programming Language :: Python :: 3.7
Classifier: Programming Language :: Python :: 3.8
Classifier: Programming Language :: Python :: 3.9
Classifier: Programming Language :: Python :: 3.10
Classifier: Programming Language :: Python :: 3.11
Classifier: Programming Language :: Python :: Implementation :: CPython
Classifier: Programming Language :: Python :: Implementation :: PyPy
Requires-Python: >=3.7
License-File: LICENSE
Requires-Dist: typing-extensions (<5.0,>=4.5.0)
Provides-Extra: tests
Requires-Dist: pytest (<8.0,>=7.2.1) ; extra == 'tests'
Requires-Dist: hypothesis (<7.0,>=6.68.2) ; extra == 'tests'
